{
  "updated_at": "2026-07-15T18:12:14.714401+00:00",
  "stocks": [
    {
      "ticker": "MU",
      "price": 913.5700073242188,
      "market_cap": 1031740129280.0,
      "revenue_growth": 3.457,
      "earnings_growth": 13.685,
      "gross_margin": 0.72569,
      "profit_margin": 0.55906,
      "roe": 0.66638,
      "forward_pe": 6.071392,
      "trailing_pe": 20.649525,
      "target_mean": 1486.0,
      "upside": 0.6265857986651595,
      "recommendation": "strong_buy",
      "num_analysts": 42.0,
      "mom_3m": 1.002740936478379,
      "mom_6m": 1.715427574778917,
      "name": "Micron",
      "tags": [
        "semiconductor",
        "ai"
      ],
      "score": 94.0,
      "subscores": {
        "revenue_growth": 98.0,
        "earnings_growth": 100.0,
        "gross_margin": 74.0,
        "profit_margin": 98.0,
        "roe": 93.0,
        "mom_3m": 93.0,
        "mom_6m": 100.0,
        "upside": 91.0,
        "forward_pe": 93.0
      },
      "rank": 1
    },
    {
      "ticker": "CRDO",
      "price": 227.97999572753906,
      "market_cap": 42513231872.0,
      "revenue_growth": 1.57,
      "earnings_growth": 3.432,
      "gross_margin": 0.68035007,
      "profit_margin": 0.35374,
      "roe": 0.34408,
      "forward_pe": 25.405663,
      "trailing_pe": 91.192,
      "target_mean": 269.81342,
      "upside": 0.18349603060110775,
      "recommendation": "none",
      "num_analysts": 19.0,
      "mom_3m": 0.35420247972760954,
      "mom_6m": 0.5288358583191919,
      "name": "Credo Technology",
      "tags": [
        "semiconductor",
        "ai"
      ],
      "score": 77.4,
      "subscores": {
        "revenue_growth": 96.0,
        "earnings_growth": 97.0,
        "gross_margin": 67.0,
        "profit_margin": 80.0,
        "roe": 76.0,
        "mom_3m": 74.0,
        "mom_6m": 78.0,
        "upside": 41.0,
        "forward_pe": 57.0
      },
      "rank": 2
    },
    {
      "ticker": "NVDA",
      "price": 210.38999938964844,
      "market_cap": 5095856013312.0,
      "revenue_growth": 0.852,
      "earnings_growth": 2.145,
      "gross_margin": 0.74144995,
      "profit_margin": 0.62966,
      "roe": 1.14288,
      "forward_pe": 16.430391,
      "trailing_pe": 32.268406,
      "target_mean": 301.6207,
      "upside": 0.4336266023813691,
      "recommendation": "strong_buy",
      "num_analysts": 58.0,
      "mom_3m": 0.05916029009741308,
      "mom_6m": 0.12615129762742527,
      "name": "NVIDIA",
      "tags": [
        "semiconductor",
        "ai",
        "physical_ai"
      ],
      "score": 76.3,
      "subscores": {
        "revenue_growth": 84.0,
        "earnings_growth": 82.0,
        "gross_margin": 78.0,
        "profit_margin": 100.0,
        "roe": 100.0,
        "mom_3m": 39.0,
        "mom_6m": 46.0,
        "upside": 80.0,
        "forward_pe": 74.0
      },
      "rank": 3
    },
    {
      "ticker": "ALAB",
      "price": 349.6000061035156,
      "market_cap": 59924213760.0,
      "revenue_growth": 0.934,
      "earnings_growth": 1.444,
      "gross_margin": 0.75988996,
      "profit_margin": 0.26724002,
      "roe": 0.21110001,
      "forward_pe": 80.040474,
      "trailing_pe": 236.21622,
      "target_mean": 281.55865,
      "upside": -0.19462630124602676,
      "recommendation": "buy",
      "num_analysts": 22.0,
      "mom_3m": 1.0314952265853528,
      "mom_6m": 1.004012681107922,
      "name": "Astera Labs",
      "tags": [
        "semiconductor",
        "ai"
      ],
      "score": 67.8,
      "subscores": {
        "revenue_growth": 89.0,
        "earnings_growth": 76.0,
        "gross_margin": 80.0,
        "profit_margin": 63.0,
        "roe": 54.0,
        "mom_3m": 96.0,
        "mom_6m": 89.0,
        "upside": 0.0,
        "forward_pe": 13.0
      },
      "rank": 4
    },
    {
      "ticker": "AVGO",
      "price": 395.6600036621094,
      "market_cap": 1882384236544.0,
      "revenue_growth": 0.479,
      "earnings_growth": 0.854,
      "gross_margin": 0.76284,
      "profit_margin": 0.38848,
      "roe": 0.37280998,
      "forward_pe": 20.377094,
      "trailing_pe": 66.05343,
      "target_mean": 523.72894,
      "upside": 0.3236843126738189,
      "recommendation": "strong_buy",
      "num_analysts": 45.0,
      "mom_3m": -0.0010934435837582912,
      "mom_6m": 0.1577094777613297,
      "name": "Broadcom",
      "tags": [
        "semiconductor",
        "ai"
      ],
      "score": 66.2,
      "subscores": {
        "revenue_growth": 76.0,
        "earnings_growth": 61.0,
        "gross_margin": 83.0,
        "profit_margin": 87.0,
        "roe": 83.0,
        "mom_3m": 26.0,
        "mom_6m": 48.0,
        "upside": 65.0,
        "forward_pe": 70.0
      },
      "rank": 5
    },
    {
      "ticker": "PLTR",
      "price": 133.92999267578125,
      "market_cap": 321095991296.0,
      "revenue_growth": 0.847,
      "earnings_growth": 3.25,
      "gross_margin": 0.84073997,
      "profit_margin": 0.43673,
      "roe": 0.32587,
      "forward_pe": 63.949047,
      "trailing_pe": 148.82224,
      "target_mean": 183.12444,
      "upside": 0.3673146420855038,
      "recommendation": "buy",
      "num_analysts": 27.0,
      "mom_3m": -0.057826250957766834,
      "mom_6m": -0.24363253438764065,
      "name": "Palantir",
      "tags": [
        "ai"
      ],
      "score": 64.4,
      "subscores": {
        "revenue_growth": 82.0,
        "earnings_growth": 91.0,
        "gross_margin": 96.0,
        "profit_margin": 93.0,
        "roe": 67.0,
        "mom_3m": 15.0,
        "mom_6m": 15.0,
        "upside": 72.0,
        "forward_pe": 15.0
      },
      "rank": 6
    },
    {
      "ticker": "TSM",
      "price": 421.5249938964844,
      "market_cap": 2186228400128.0,
      "revenue_growth": 0.351,
      "earnings_growth": 0.584,
      "gross_margin": 0.61873,
      "profit_margin": 0.46505,
      "roe": 0.3621,
      "forward_pe": 20.773743,
      "trailing_pe": 36.59071,
      "target_mean": 498.24393,
      "upside": 0.1820032909421163,
      "recommendation": "strong_buy",
      "num_analysts": 18.0,
      "mom_3m": 0.12639864759071506,
      "mom_6m": 0.24020217786645648,
      "name": "TSMC",
      "tags": [
        "semiconductor"
      ],
      "score": 61.6,
      "subscores": {
        "revenue_growth": 67.0,
        "earnings_growth": 48.0,
        "gross_margin": 57.0,
        "profit_margin": 96.0,
        "roe": 80.0,
        "mom_3m": 52.0,
        "mom_6m": 54.0,
        "upside": 37.0,
        "forward_pe": 63.0
      },
      "rank": 7
    },
    {
      "ticker": "TER",
      "price": 341.2049865722656,
      "market_cap": 53412966400.0,
      "revenue_growth": 0.87,
      "earnings_growth": 3.148,
      "gross_margin": 0.58702,
      "profit_margin": 0.22553,
      "roe": 0.2875,
      "forward_pe": 34.68581,
      "trailing_pe": 63.186108,
      "target_mean": 423.41177,
      "upside": 0.2409307796277571,
      "recommendation": "buy",
      "num_analysts": 17.0,
      "mom_3m": -0.06473624061378092,
      "mom_6m": 0.4996775130093003,
      "name": "Teradyne",
      "tags": [
        "semiconductor",
        "physical_ai"
      ],
      "score": 61.1,
      "subscores": {
        "revenue_growth": 87.0,
        "earnings_growth": 88.0,
        "gross_margin": 50.0,
        "profit_margin": 54.0,
        "roe": 63.0,
        "mom_3m": 13.0,
        "mom_6m": 74.0,
        "upside": 54.0,
        "forward_pe": 35.0
      },
      "rank": 8
    },
    {
      "ticker": "PTC",
      "price": 123.47000122070312,
      "market_cap": 14261499904.0,
      "revenue_growth": 0.217,
      "earnings_growth": 2.689,
      "gross_margin": 0.84713,
      "profit_margin": 0.41575,
      "roe": 0.344,
      "forward_pe": 14.307748,
      "trailing_pe": 11.860711,
      "target_mean": 177.5,
      "upside": 0.43759616299604653,
      "recommendation": "buy",
      "num_analysts": 20.0,
      "mom_3m": -0.09598770269873214,
      "mom_6m": -0.26017136034358745,
      "name": "PTC Inc",
      "tags": [
        "physical_ai",
        "ai"
      ],
      "score": 59.7,
      "subscores": {
        "revenue_growth": 38.0,
        "earnings_growth": 85.0,
        "gross_margin": 98.0,
        "profit_margin": 91.0,
        "roe": 74.0,
        "mom_3m": 11.0,
        "mom_6m": 13.0,
        "upside": 83.0,
        "forward_pe": 80.0
      },
      "rank": 9
    },
    {
      "ticker": "META",
      "price": 676.0700073242188,
      "market_cap": 1716151910400.0,
      "revenue_growth": 0.331,
      "earnings_growth": 0.624,
      "gross_margin": 0.81941,
      "profit_margin": 0.32837,
      "roe": 0.32930002,
      "forward_pe": 18.60967,
      "trailing_pe": 24.584364,
      "target_mean": 826.63416,
      "upside": 0.2227049729238706,
      "recommendation": "strong_buy",
      "num_analysts": 58.0,
      "mom_3m": 0.007618680978104253,
      "mom_6m": 0.09097292288563574,
      "name": "Meta Platforms",
      "tags": [
        "ai"
      ],
      "score": 58.7,
      "subscores": {
        "revenue_growth": 60.0,
        "earnings_growth": 52.0,
        "gross_margin": 91.0,
        "profit_margin": 78.0,
        "roe": 70.0,
        "mom_3m": 30.0,
        "mom_6m": 37.0,
        "upside": 50.0,
        "forward_pe": 72.0
      },
      "rank": 10
    },
    {
      "ticker": "AMD",
      "price": 531.8900146484375,
      "market_cap": 867300147200.0,
      "revenue_growth": 0.378,
      "earnings_growth": 0.912,
      "gross_margin": 0.5306,
      "profit_margin": 0.13374,
      "roe": 0.08063,
      "forward_pe": 39.89996,
      "trailing_pe": 176.70764,
      "target_mean": 525.40424,
      "upside": -0.012193826674344432,
      "recommendation": "strong_buy",
      "num_analysts": 47.0,
      "mom_3m": 1.0606308101275044,
      "mom_6m": 1.3336697916879365,
      "name": "AMD",
      "tags": [
        "semiconductor",
        "ai"
      ],
      "score": 56.6,
      "subscores": {
        "revenue_growth": 73.0,
        "earnings_growth": 64.0,
        "gross_margin": 37.0,
        "profit_margin": 41.0,
        "roe": 30.0,
        "mom_3m": 98.0,
        "mom_6m": 93.0,
        "upside": 7.0,
        "forward_pe": 28.0
      },
      "rank": 11
    },
    {
      "ticker": "ADI",
      "price": 390.760009765625,
      "market_cap": 190334140416.0,
      "revenue_growth": 0.372,
      "earnings_growth": 1.105,
      "gross_margin": 0.64491,
      "profit_margin": 0.26007998,
      "roe": 0.09639,
      "forward_pe": 26.053377,
      "trailing_pe": 58.14881,
      "target_mean": 454.0,
      "upside": 0.16183843958931687,
      "recommendation": "buy",
      "num_analysts": 30.0,
      "mom_3m": 0.12614341019479602,
      "mom_6m": 0.3010830415883661,
      "name": "Analog Devices",
      "tags": [
        "semiconductor"
      ],
      "score": 55.9,
      "subscores": {
        "revenue_growth": 71.0,
        "earnings_growth": 70.0,
        "gross_margin": 59.0,
        "profit_margin": 61.0,
        "roe": 33.0,
        "mom_3m": 50.0,
        "mom_6m": 57.0,
        "upside": 35.0,
        "forward_pe": 50.0
      },
      "rank": 12
    },
    {
      "ticker": "SMCI",
      "price": 27.135000228881836,
      "market_cap": 17549664256.0,
      "revenue_growth": 1.227,
      "earnings_growth": 3.26,
      "gross_margin": 0.08394,
      "profit_margin": 0.03701,
      "roe": 0.17877,
      "forward_pe": 8.553152,
      "trailing_pe": 14.278947,
      "target_mean": 37.375,
      "upside": 0.37737238565485454,
      "recommendation": "hold",
      "num_analysts": 16.0,
      "mom_3m": -0.005679761137615702,
      "mom_6m": -0.07766824750124035,
      "name": "Super Micro",
      "tags": [
        "semiconductor",
        "ai"
      ],
      "score": 55.7,
      "subscores": {
        "revenue_growth": 91.0,
        "earnings_growth": 94.0,
        "gross_margin": 4.0,
        "profit_margin": 22.0,
        "roe": 48.0,
        "mom_3m": 24.0,
        "mom_6m": 30.0,
        "upside": 74.0,
        "forward_pe": 91.0
      },
      "rank": 13
    },
    {
      "ticker": "DDOG",
      "price": 265.56500244140625,
      "market_cap": 94530568192.0,
      "revenue_growth": 0.322,
      "earnings_growth": 1.04,
      "gross_margin": 0.79906,
      "profit_margin": 0.03695,
      "roe": 0.039300002,
      "forward_pe": 92.169106,
      "trailing_pe": 698.8553,
      "target_mean": 247.68239,
      "upside": -0.06733798609382591,
      "recommendation": "strong_buy",
      "num_analysts": 46.0,
      "mom_3m": 1.193664363101207,
      "mom_6m": 1.1972943993073324,
      "name": "Datadog",
      "tags": [
        "ai"
      ],
      "score": 54.7,
      "subscores": {
        "revenue_growth": 58.0,
        "earnings_growth": 67.0,
        "gross_margin": 89.0,
        "profit_margin": 20.0,
        "roe": 22.0,
        "mom_3m": 100.0,
        "mom_6m": 91.0,
        "upside": 4.0,
        "forward_pe": 9.0
      },
      "rank": 14
    },
    {
      "ticker": "LRCX",
      "price": 332.69500732421875,
      "market_cap": 416058736640.0,
      "revenue_growth": 0.238,
      "earnings_growth": 0.408,
      "gross_margin": 0.49979,
      "profit_margin": 0.30938998,
      "roe": 0.66762,
      "forward_pe": 41.166515,
      "trailing_pe": 62.77264,
      "target_mean": 364.5484,
      "upside": 0.09574352477354564,
      "recommendation": "buy",
      "num_analysts": 31.0,
      "mom_3m": 0.25557908780582705,
      "mom_6m": 0.5327551321831268,
      "name": "Lam Research",
      "tags": [
        "semiconductor"
      ],
      "score": 54.3,
      "subscores": {
        "revenue_growth": 49.0,
        "earnings_growth": 39.0,
        "gross_margin": 28.0,
        "profit_margin": 76.0,
        "roe": 96.0,
        "mom_3m": 63.0,
        "mom_6m": 80.0,
        "upside": 26.0,
        "forward_pe": 26.0
      },
      "rank": 15
    },
    {
      "ticker": "ARM",
      "price": 275.45001220703125,
      "market_cap": 294202310656.0,
      "revenue_growth": 0.201,
      "earnings_growth": 0.479,
      "gross_margin": 0.97541,
      "profit_margin": 0.18374,
      "roe": 0.119540006,
      "forward_pe": 89.3938,
      "trailing_pe": 327.9167,
      "target_mean": 298.83838,
      "upside": 0.08490966330177452,
      "recommendation": "buy",
      "num_analysts": 37.0,
      "mom_3m": 0.7286934764509592,
      "mom_6m": 1.6205880563937898,
      "name": "Arm Holdings",
      "tags": [
        "semiconductor",
        "ai"
      ],
      "score": 52.9,
      "subscores": {
        "revenue_growth": 31.0,
        "earnings_growth": 42.0,
        "gross_margin": 100.0,
        "profit_margin": 43.0,
        "roe": 37.0,
        "mom_3m": 89.0,
        "mom_6m": 98.0,
        "upside": 24.0,
        "forward_pe": 11.0
      },
      "rank": 16
    },
    {
      "ticker": "GOOGL",
      "price": 371.8800048828125,
      "market_cap": 4537892995072.0,
      "revenue_growth": 0.218,
      "earnings_growth": 0.82,
      "gross_margin": 0.60368,
      "profit_margin": 0.37919,
      "roe": 0.38884997,
      "forward_pe": 25.486876,
      "trailing_pe": 28.344513,
      "target_mean": 431.7213,
      "upside": 0.1609156026983618,
      "recommendation": "strong_buy",
      "num_analysts": 53.0,
      "mom_3m": 0.1037675742566635,
      "mom_6m": 0.11894960313524994,
      "name": "Alphabet",
      "tags": [
        "ai"
      ],
      "score": 52.9,
      "subscores": {
        "revenue_growth": 40.0,
        "earnings_growth": 58.0,
        "gross_margin": 52.0,
        "profit_margin": 85.0,
        "roe": 85.0,
        "mom_3m": 41.0,
        "mom_6m": 43.0,
        "upside": 33.0,
        "forward_pe": 54.0
      },
      "rank": 17
    },
    {
      "ticker": "MRVL",
      "price": 207.83999633789062,
      "market_cap": 186577059840.0,
      "revenue_growth": 0.276,
      "earnings_growth": -0.804,
      "gross_margin": 0.51502997,
      "profit_margin": 0.28986,
      "roe": 0.16028,
      "forward_pe": 33.53147,
      "trailing_pe": 71.43471,
      "target_mean": 252.56422,
      "upside": 0.2151858374237079,
      "recommendation": "strong_buy",
      "num_analysts": 40.0,
      "mom_3m": 0.5445116606587843,
      "mom_6m": 1.587650349805784,
      "name": "Marvell",
      "tags": [
        "semiconductor",
        "ai"
      ],
      "score": 51.9,
      "subscores": {
        "revenue_growth": 56.0,
        "earnings_growth": 0.0,
        "gross_margin": 33.0,
        "profit_margin": 67.0,
        "roe": 39.0,
        "mom_3m": 85.0,
        "mom_6m": 96.0,
        "upside": 48.0,
        "forward_pe": 39.0
      },
      "rank": 18
    },
    {
      "ticker": "OUST",
      "price": 39.599998474121094,
      "market_cap": 2664875008.0,
      "revenue_growth": 0.489,
      "earnings_growth": null,
      "gross_margin": 0.47694,
      "profit_margin": -0.30122,
      "roe": -0.25171,
      "forward_pe": -879.99994,
      "trailing_pe": null,
      "target_mean": 46.85714,
      "upside": 0.18326115670487986,
      "recommendation": "none",
      "num_analysts": 7.0,
      "mom_3m": 0.6202945011780063,
      "mom_6m": 0.44525543888475516,
      "name": "Ouster",
      "tags": [
        "physical_ai"
      ],
      "score": 51.3,
      "subscores": {
        "revenue_growth": 78.0,
        "earnings_growth": 50.0,
        "gross_margin": 20.0,
        "profit_margin": 0.0,
        "roe": 7.0,
        "mom_3m": 87.0,
        "mom_6m": 67.0,
        "upside": 39.0,
        "forward_pe": 100.0
      },
      "rank": 19
    },
    {
      "ticker": "MCHP",
      "price": 85.91000366210938,
      "market_cap": 46649851904.0,
      "revenue_growth": 0.351,
      "earnings_growth": null,
      "gross_margin": 0.57735,
      "profit_margin": 0.048800003,
      "roe": 0.03405,
      "forward_pe": 20.68471,
      "trailing_pe": 390.50003,
      "target_mean": 113.375,
      "upside": 0.3196949734272223,
      "recommendation": "buy",
      "num_analysts": 24.0,
      "mom_3m": 0.15909776367877693,
      "mom_6m": 0.16654894536702636,
      "name": "Microchip",
      "tags": [
        "semiconductor"
      ],
      "score": 51.1,
      "subscores": {
        "revenue_growth": 69.0,
        "earnings_growth": 50.0,
        "gross_margin": 48.0,
        "profit_margin": 26.0,
        "roe": 20.0,
        "mom_3m": 57.0,
        "mom_6m": 50.0,
        "upside": 63.0,
        "forward_pe": 65.0
      },
      "rank": 20
    },
    {
      "ticker": "QCOM",
      "price": 178.27499389648438,
      "market_cap": 187901837312.0,
      "revenue_growth": -0.035,
      "earnings_growth": 1.73,
      "gross_margin": 0.54799,
      "profit_margin": 0.22308001,
      "roe": 0.36083,
      "forward_pe": 16.143492,
      "trailing_pe": 19.169353,
      "target_mean": 221.9,
      "upside": 0.2447062549268495,
      "recommendation": "hold",
      "num_analysts": 30.0,
      "mom_3m": 0.3448586574837944,
      "mom_6m": 0.11582054583324708,
      "name": "Qualcomm",
      "tags": [
        "semiconductor"
      ],
      "score": 49.1,
      "subscores": {
        "revenue_growth": 0.0,
        "earnings_growth": 79.0,
        "gross_margin": 39.0,
        "profit_margin": 52.0,
        "roe": 78.0,
        "mom_3m": 70.0,
        "mom_6m": 41.0,
        "upside": 57.0,
        "forward_pe": 76.0
      },
      "rank": 21
    },
    {
      "ticker": "TXN",
      "price": 301.010009765625,
      "market_cap": 273947049984.0,
      "revenue_growth": 0.186,
      "earnings_growth": 0.313,
      "gross_margin": 0.57322,
      "profit_margin": 0.29108,
      "roe": 0.32347,
      "forward_pe": 31.442495,
      "trailing_pe": 51.54281,
      "target_mean": 299.875,
      "upside": -0.0037706711697353956,
      "recommendation": "buy",
      "num_analysts": 32.0,
      "mom_3m": 0.3987677338393585,
      "mom_6m": 0.6101640103751838,
      "name": "Texas Instruments",
      "tags": [
        "semiconductor"
      ],
      "score": 48.6,
      "subscores": {
        "revenue_growth": 29.0,
        "earnings_growth": 27.0,
        "gross_margin": 46.0,
        "profit_margin": 70.0,
        "roe": 65.0,
        "mom_3m": 78.0,
        "mom_6m": 85.0,
        "upside": 9.0,
        "forward_pe": 46.0
      },
      "rank": 22
    },
    {
      "ticker": "MSFT",
      "price": 396.20001220703125,
      "market_cap": 2943220187136.0,
      "revenue_growth": 0.183,
      "earnings_growth": 0.234,
      "gross_margin": 0.68309,
      "profit_margin": 0.39341998,
      "roe": 0.34013999,
      "forward_pe": 20.456388,
      "trailing_pe": 23.612036,
      "target_mean": 559.86035,
      "upside": 0.41307504480199086,
      "recommendation": "strong_buy",
      "num_analysts": 55.0,
      "mom_3m": -0.03443865285162917,
      "mom_6m": -0.12853237310011645,
      "name": "Microsoft",
      "tags": [
        "ai"
      ],
      "score": 48.2,
      "subscores": {
        "revenue_growth": 27.0,
        "earnings_growth": 24.0,
        "gross_margin": 70.0,
        "profit_margin": 89.0,
        "roe": 72.0,
        "mom_3m": 22.0,
        "mom_6m": 26.0,
        "upside": 76.0,
        "forward_pe": 67.0
      },
      "rank": 23
    },
    {
      "ticker": "NXPI",
      "price": 281.3800048828125,
      "market_cap": 71040311296.0,
      "revenue_growth": 0.122,
      "earnings_growth": 1.307,
      "gross_margin": 0.55632,
      "profit_margin": 0.21031,
      "roe": 0.25812998,
      "forward_pe": 15.80767,
      "trailing_pe": 26.926317,
      "target_mean": 310.31033,
      "upside": 0.10281585263756132,
      "recommendation": "buy",
      "num_analysts": 29.0,
      "mom_3m": 0.34836656285609324,
      "mom_6m": 0.18943724370011106,
      "name": "NXP Semiconductors",
      "tags": [
        "semiconductor",
        "physical_ai"
      ],
      "score": 47.5,
      "subscores": {
        "revenue_growth": 11.0,
        "earnings_growth": 73.0,
        "gross_margin": 43.0,
        "profit_margin": 50.0,
        "roe": 59.0,
        "mom_3m": 72.0,
        "mom_6m": 52.0,
        "upside": 28.0,
        "forward_pe": 78.0
      },
      "rank": 24
    },
    {
      "ticker": "MPWR",
      "price": 1349.880126953125,
      "market_cap": 66319609856.0,
      "revenue_growth": 0.261,
      "earnings_growth": 0.395,
      "gross_margin": 0.55175,
      "profit_margin": 0.22984,
      "roe": 0.19574,
      "forward_pe": 44.274654,
      "trailing_pe": 97.11368,
      "target_mean": 1789.2307,
      "upside": 0.3254737693179861,
      "recommendation": "none",
      "num_analysts": 13.0,
      "mom_3m": -0.0007835986442442655,
      "mom_6m": 0.34184160793090657,
      "name": "Monolithic Power",
      "tags": [
        "semiconductor"
      ],
      "score": 47.4,
      "subscores": {
        "revenue_growth": 53.0,
        "earnings_growth": 33.0,
        "gross_margin": 41.0,
        "profit_margin": 57.0,
        "roe": 52.0,
        "mom_3m": 28.0,
        "mom_6m": 63.0,
        "upside": 67.0,
        "forward_pe": 22.0
      },
      "rank": 25
    },
    {
      "ticker": "ORCL",
      "price": 133.01499938964844,
      "market_cap": 383145869312.0,
      "revenue_growth": 0.206,
      "earnings_growth": 0.219,
      "gross_margin": 0.65822,
      "profit_margin": 0.25368,
      "roe": 0.53376,
      "forward_pe": 12.179076,
      "trailing_pe": 22.815609,
      "target_mean": 251.8495,
      "upside": 0.8933917314260393,
      "recommendation": "buy",
      "num_analysts": 40.0,
      "mom_3m": -0.2139582145711043,
      "mom_6m": -0.2944749809035846,
      "name": "Oracle",
      "tags": [
        "ai"
      ],
      "score": 47.2,
      "subscores": {
        "revenue_growth": 36.0,
        "earnings_growth": 21.0,
        "gross_margin": 61.0,
        "profit_margin": 59.0,
        "roe": 91.0,
        "mom_3m": 7.0,
        "mom_6m": 7.0,
        "upside": 98.0,
        "forward_pe": 87.0
      },
      "rank": 26
    },
    {
      "ticker": "AUR",
      "price": 6.039999961853027,
      "market_cap": 11845666816.0,
      "revenue_growth": null,
      "earnings_growth": null,
      "gross_margin": 0.0,
      "profit_margin": 0.0,
      "roe": -0.44332,
      "forward_pe": -14.267829,
      "trailing_pe": null,
      "target_mean": 11.21583,
      "upside": 0.8569255084165708,
      "recommendation": "buy",
      "num_analysts": 12.0,
      "mom_3m": 0.13962259329948457,
      "mom_6m": 0.321662961701213,
      "name": "Aurora Innovation",
      "tags": [
        "physical_ai"
      ],
      "score": 46.0,
      "subscores": {
        "revenue_growth": 50.0,
        "earnings_growth": 50.0,
        "gross_margin": 0.0,
        "profit_margin": 15.0,
        "roe": 4.0,
        "mom_3m": 54.0,
        "mom_6m": 61.0,
        "upside": 96.0,
        "forward_pe": 98.0
      },
      "rank": 27
    },
    {
      "ticker": "NET",
      "price": 275.1400146484375,
      "market_cap": 97658077184.0,
      "revenue_growth": 0.335,
      "earnings_growth": null,
      "gross_margin": 0.73327005,
      "profit_margin": -0.037249997,
      "roe": -0.05876,
      "forward_pe": 174.29037,
      "trailing_pe": null,
      "target_mean": 250.26161,
      "upside": -0.09042088872542264,
      "recommendation": "buy",
      "num_analysts": 31.0,
      "mom_3m": 0.4471151716322803,
      "mom_6m": 0.4941892883698178,
      "name": "Cloudflare",
      "tags": [
        "ai"
      ],
      "score": 45.8,
      "subscores": {
        "revenue_growth": 64.0,
        "earnings_growth": 50.0,
        "gross_margin": 76.0,
        "profit_margin": 9.0,
        "roe": 13.0,
        "mom_3m": 80.0,
        "mom_6m": 72.0,
        "upside": 2.0,
        "forward_pe": 2.0
      },
      "rank": 28
    },
    {
      "ticker": "PATH",
      "price": 11.925000190734863,
      "market_cap": 6178584064.0,
      "revenue_growth": 0.173,
      "earnings_growth": null,
      "gross_margin": 0.8305,
      "profit_margin": 0.19578,
      "roe": 0.18181999,
      "forward_pe": 13.14745,
      "trailing_pe": 19.875,
      "target_mean": 13.24875,
      "upside": 0.11100627153814413,
      "recommendation": "none",
      "num_analysts": 16.0,
      "mom_3m": 0.12393973389339763,
      "mom_6m": -0.19371195256982343,
      "name": "UiPath",
      "tags": [
        "ai",
        "physical_ai"
      ],
      "score": 45.7,
      "subscores": {
        "revenue_growth": 24.0,
        "earnings_growth": 50.0,
        "gross_margin": 93.0,
        "profit_margin": 48.0,
        "roe": 50.0,
        "mom_3m": 48.0,
        "mom_6m": 20.0,
        "upside": 30.0,
        "forward_pe": 83.0
      },
      "rank": 29
    },
    {
      "ticker": "AMAT",
      "price": 579.1300048828125,
      "market_cap": 459742183424.0,
      "revenue_growth": 0.114,
      "earnings_growth": 0.335,
      "gross_margin": 0.48956,
      "profit_margin": 0.29314,
      "roe": 0.39692003,
      "forward_pe": 34.58355,
      "trailing_pe": 54.627354,
      "target_mean": 612.2,
      "upside": 0.05710288681015463,
      "recommendation": "strong_buy",
      "num_analysts": 35.0,
      "mom_3m": 0.4707298750816762,
      "mom_6m": 0.8195223355628483,
      "name": "Applied Materials",
      "tags": [
        "semiconductor"
      ],
      "score": 45.4,
      "subscores": {
        "revenue_growth": 4.0,
        "earnings_growth": 30.0,
        "gross_margin": 26.0,
        "profit_margin": 72.0,
        "roe": 87.0,
        "mom_3m": 83.0,
        "mom_6m": 87.0,
        "upside": 15.0,
        "forward_pe": 37.0
      },
      "rank": 30
    },
    {
      "ticker": "SNOW",
      "price": 270.9198913574219,
      "market_cap": 93900832768.0,
      "revenue_growth": 0.335,
      "earnings_growth": null,
      "gross_margin": 0.67144996,
      "profit_margin": -0.23786,
      "roe": -0.54869,
      "forward_pe": 100.839294,
      "trailing_pe": null,
      "target_mean": 292.53418,
      "upside": 0.07978110626828294,
      "recommendation": "none",
      "num_analysts": 48.0,
      "mom_3m": 0.8751377309584343,
      "mom_6m": 0.3041296052451332,
      "name": "Snowflake",
      "tags": [
        "ai"
      ],
      "score": 44.8,
      "subscores": {
        "revenue_growth": 62.0,
        "earnings_growth": 50.0,
        "gross_margin": 65.0,
        "profit_margin": 4.0,
        "roe": 0.0,
        "mom_3m": 91.0,
        "mom_6m": 59.0,
        "upside": 22.0,
        "forward_pe": 7.0
      },
      "rank": 31
    },
    {
      "ticker": "SERV",
      "price": 5.775000095367432,
      "market_cap": 491396096.0,
      "revenue_growth": 5.782,
      "earnings_growth": null,
      "gross_margin": 0.0,
      "profit_margin": 0.0,
      "roe": -0.51955,
      "forward_pe": -3.2083335,
      "trailing_pe": null,
      "target_mean": 18.45,
      "upside": 2.1948051420466905,
      "recommendation": "none",
      "num_analysts": 8.0,
      "mom_3m": -0.395920518631214,
      "mom_6m": -0.6039094564069449,
      "name": "Serve Robotics",
      "tags": [
        "physical_ai"
      ],
      "score": 44.1,
      "subscores": {
        "revenue_growth": 100.0,
        "earnings_growth": 50.0,
        "gross_margin": 2.0,
        "profit_margin": 17.0,
        "roe": 2.0,
        "mom_3m": 0.0,
        "mom_6m": 2.0,
        "upside": 100.0,
        "forward_pe": 96.0
      },
      "rank": 32
    },
    {
      "ticker": "KLAC",
      "price": 224.02999877929688,
      "market_cap": 292680761344.0,
      "revenue_growth": 0.115,
      "earnings_growth": 0.118,
      "gross_margin": 0.61446,
      "profit_margin": 0.35661998,
      "roe": 0.94975996,
      "forward_pe": 43.758667,
      "trailing_pe": 63.6527,
      "target_mean": 231.10715,
      "upside": 0.03159019443496569,
      "recommendation": "buy",
      "num_analysts": 28.0,
      "mom_3m": 0.28319120838398826,
      "mom_6m": 0.45380725517849707,
      "name": "KLA Corp",
      "tags": [
        "semiconductor"
      ],
      "score": 43.8,
      "subscores": {
        "revenue_growth": 7.0,
        "earnings_growth": 12.0,
        "gross_margin": 54.0,
        "profit_margin": 83.0,
        "roe": 98.0,
        "mom_3m": 65.0,
        "mom_6m": 70.0,
        "upside": 13.0,
        "forward_pe": 24.0
      },
      "rank": 33
    },
    {
      "ticker": "MDB",
      "price": 333.2049865722656,
      "market_cap": 26800320512.0,
      "revenue_growth": 0.252,
      "earnings_growth": null,
      "gross_margin": 0.71970004,
      "profit_margin": -0.01118,
      "roe": -0.00975,
      "forward_pe": 45.406353,
      "trailing_pe": null,
      "target_mean": 396.21222,
      "upside": 0.18909450928661098,
      "recommendation": "buy",
      "num_analysts": 36.0,
      "mom_3m": 0.36525850162016016,
      "mom_6m": -0.1438721065737778,
      "name": "MongoDB",
      "tags": [
        "ai"
      ],
      "score": 43.3,
      "subscores": {
        "revenue_growth": 51.0,
        "earnings_growth": 50.0,
        "gross_margin": 72.0,
        "profit_margin": 11.0,
        "roe": 17.0,
        "mom_3m": 76.0,
        "mom_6m": 24.0,
        "upside": 43.0,
        "forward_pe": 20.0
      },
      "rank": 34
    },
    {
      "ticker": "NOW",
      "price": 104.89610290527344,
      "market_cap": 108180193280.0,
      "revenue_growth": 0.221,
      "earnings_growth": 0.023,
      "gross_margin": 0.76562,
      "profit_margin": 0.12586,
      "roe": 0.1607,
      "forward_pe": 20.880497,
      "trailing_pe": 62.43816,
      "target_mean": 140.94849,
      "upside": 0.34369615358621775,
      "recommendation": "strong_buy",
      "num_analysts": 46.0,
      "mom_3m": 0.11366493456168292,
      "mom_6m": -0.20030415209605645,
      "name": "ServiceNow",
      "tags": [
        "ai"
      ],
      "score": 43.2,
      "subscores": {
        "revenue_growth": 42.0,
        "earnings_growth": 3.0,
        "gross_margin": 85.0,
        "profit_margin": 39.0,
        "roe": 41.0,
        "mom_3m": 46.0,
        "mom_6m": 17.0,
        "upside": 70.0,
        "forward_pe": 61.0
      },
      "rank": 35
    },
    {
      "ticker": "CRM",
      "price": 167.47999572753906,
      "market_cap": 137166118912.0,
      "revenue_growth": 0.133,
      "earnings_growth": 0.522,
      "gross_margin": 0.77643996,
      "profit_margin": 0.18733,
      "roe": 0.16908,
      "forward_pe": 10.787608,
      "trailing_pe": 19.40672,
      "target_mean": 245.41193,
      "upside": 0.46532085180634164,
      "recommendation": "buy",
      "num_analysts": 52.0,
      "mom_3m": -0.054548143628117995,
      "mom_6m": -0.279183812587262,
      "name": "Salesforce",
      "tags": [
        "ai"
      ],
      "score": 43.2,
      "subscores": {
        "revenue_growth": 16.0,
        "earnings_growth": 45.0,
        "gross_margin": 87.0,
        "profit_margin": 46.0,
        "roe": 43.0,
        "mom_3m": 17.0,
        "mom_6m": 11.0,
        "upside": 85.0,
        "forward_pe": 89.0
      },
      "rank": 36
    },
    {
      "ticker": "ASML",
      "price": 1792.8499755859375,
      "market_cap": 690996051968.0,
      "revenue_growth": 0.132,
      "earnings_growth": 0.192,
      "gross_margin": 0.52603,
      "profit_margin": 0.29713,
      "roe": 0.52236,
      "forward_pe": 35.733883,
      "trailing_pe": 60.815807,
      "target_mean": 1910.8226,
      "upside": 0.06580172687093166,
      "recommendation": "strong_buy",
      "num_analysts": 15.0,
      "mom_3m": 0.21258088123350638,
      "mom_6m": 0.35110831247001584,
      "name": "ASML",
      "tags": [
        "semiconductor"
      ],
      "score": 42.2,
      "subscores": {
        "revenue_growth": 13.0,
        "earnings_growth": 18.0,
        "gross_margin": 35.0,
        "profit_margin": 74.0,
        "roe": 89.0,
        "mom_3m": 61.0,
        "mom_6m": 65.0,
        "upside": 17.0,
        "forward_pe": 33.0
      },
      "rank": 37
    },
    {
      "ticker": "ISRG",
      "price": 389.45001220703125,
      "market_cap": 137928720384.0,
      "revenue_growth": 0.23,
      "earnings_growth": 0.188,
      "gross_margin": 0.66292,
      "profit_margin": 0.28152,
      "roe": 0.17232999,
      "forward_pe": 33.040386,
      "trailing_pe": 47.26335,
      "target_mean": 558.00934,
      "upside": 0.4328137694430543,
      "recommendation": "buy",
      "num_analysts": 30.0,
      "mom_3m": -0.16848145787966806,
      "mom_6m": -0.2805815330721707,
      "name": "Intuitive Surgical",
      "tags": [
        "physical_ai"
      ],
      "score": 40.3,
      "subscores": {
        "revenue_growth": 44.0,
        "earnings_growth": 15.0,
        "gross_margin": 63.0,
        "profit_margin": 65.0,
        "roe": 46.0,
        "mom_3m": 9.0,
        "mom_6m": 9.0,
        "upside": 78.0,
        "forward_pe": 41.0
      },
      "rank": 38
    },
    {
      "ticker": "AVAV",
      "price": 141.0500030517578,
      "market_cap": 7138263040.0,
      "revenue_growth": 1.333,
      "earnings_growth": null,
      "gross_margin": 0.25325,
      "profit_margin": -0.13411,
      "roe": -0.10029,
      "forward_pe": 31.126009,
      "trailing_pe": null,
      "target_mean": 245.3839,
      "upside": 0.7396943969576324,
      "recommendation": "buy",
      "num_analysts": 18.0,
      "mom_3m": -0.2891341379226283,
      "mom_6m": -0.6274136875007155,
      "name": "AeroVironment",
      "tags": [
        "physical_ai"
      ],
      "score": 40.0,
      "subscores": {
        "revenue_growth": 93.0,
        "earnings_growth": 50.0,
        "gross_margin": 11.0,
        "profit_margin": 7.0,
        "roe": 11.0,
        "mom_3m": 2.0,
        "mom_6m": 0.0,
        "upside": 93.0,
        "forward_pe": 48.0
      },
      "rank": 39
    },
    {
      "ticker": "RKLB",
      "price": 76.97000122070312,
      "market_cap": 48089673728.0,
      "revenue_growth": 0.635,
      "earnings_growth": null,
      "gross_margin": 0.36556,
      "profit_margin": -0.26872,
      "roe": -0.13549,
      "forward_pe": 2565.5266,
      "trailing_pe": null,
      "target_mean": 116.57143,
      "upside": 0.514504718088078,
      "recommendation": "buy",
      "num_analysts": 14.0,
      "mom_3m": 0.0457880817452323,
      "mom_6m": -0.1519391867667499,
      "name": "Rocket Lab",
      "tags": [
        "physical_ai"
      ],
      "score": 39.7,
      "subscores": {
        "revenue_growth": 80.0,
        "earnings_growth": 50.0,
        "gross_margin": 13.0,
        "profit_margin": 2.0,
        "roe": 9.0,
        "mom_3m": 37.0,
        "mom_6m": 22.0,
        "upside": 87.0,
        "forward_pe": 0.0
      },
      "rank": 40
    },
    {
      "ticker": "AMZN",
      "price": 254.88499450683594,
      "market_cap": 2741825961984.0,
      "revenue_growth": 0.166,
      "earnings_growth": 0.748,
      "gross_margin": 0.50604,
      "profit_margin": 0.12224,
      "roe": 0.24285,
      "forward_pe": 25.781612,
      "trailing_pe": 30.45221,
      "target_mean": 314.2654,
      "upside": 0.23296940491948614,
      "recommendation": "strong_buy",
      "num_analysts": 61.0,
      "mom_3m": 0.02569414288465155,
      "mom_6m": 0.07013604141719032,
      "name": "Amazon",
      "tags": [
        "ai"
      ],
      "score": 39.2,
      "subscores": {
        "revenue_growth": 22.0,
        "earnings_growth": 55.0,
        "gross_margin": 30.0,
        "profit_margin": 35.0,
        "roe": 57.0,
        "mom_3m": 35.0,
        "mom_6m": 35.0,
        "upside": 52.0,
        "forward_pe": 52.0
      },
      "rank": 41
    },
    {
      "ticker": "ON",
      "price": 93.45999908447266,
      "market_cap": 36375232512.0,
      "revenue_growth": 0.047,
      "earnings_growth": null,
      "gross_margin": 0.42665002,
      "profit_margin": 0.09462,
      "roe": 0.074939996,
      "forward_pe": 21.531548,
      "trailing_pe": 68.72426,
      "target_mean": 113.52,
      "upside": 0.2146372898783826,
      "recommendation": "buy",
      "num_analysts": 25.0,
      "mom_3m": 0.29034928469818166,
      "mom_6m": 0.5504313367134877,
      "name": "onsemi",
      "tags": [
        "semiconductor",
        "physical_ai"
      ],
      "score": 38.7,
      "subscores": {
        "revenue_growth": 2.0,
        "earnings_growth": 50.0,
        "gross_margin": 17.0,
        "profit_margin": 33.0,
        "roe": 28.0,
        "mom_3m": 67.0,
        "mom_6m": 83.0,
        "upside": 46.0,
        "forward_pe": 59.0
      },
      "rank": 42
    },
    {
      "ticker": "COHR",
      "price": 296.3800048828125,
      "market_cap": 57983586304.0,
      "revenue_growth": 0.205,
      "earnings_growth": null,
      "gross_margin": 0.36990002,
      "profit_margin": 0.07102,
      "roe": 0.04718,
      "forward_pe": 35.990417,
      "trailing_pe": 140.46446,
      "target_mean": 387.36176,
      "upside": 0.3069766975446313,
      "recommendation": "buy",
      "num_analysts": 22.0,
      "mom_3m": -0.038351741908039694,
      "mom_6m": 0.5124514938171771,
      "name": "Coherent",
      "tags": [
        "semiconductor",
        "ai"
      ],
      "score": 37.1,
      "subscores": {
        "revenue_growth": 33.0,
        "earnings_growth": 50.0,
        "gross_margin": 15.0,
        "profit_margin": 28.0,
        "roe": 24.0,
        "mom_3m": 20.0,
        "mom_6m": 76.0,
        "upside": 59.0,
        "forward_pe": 30.0
      },
      "rank": 43
    },
    {
      "ticker": "ROK",
      "price": 461.67999267578125,
      "market_cap": 51372957696.0,
      "revenue_growth": 0.119,
      "earnings_growth": 0.396,
      "gross_margin": 0.48921,
      "profit_margin": 0.12358,
      "roe": 0.27183,
      "forward_pe": 31.560589,
      "trailing_pe": 47.94185,
      "target_mean": 472.16193,
      "upside": 0.022703902032808587,
      "recommendation": "buy",
      "num_analysts": 26.0,
      "mom_3m": 0.16533517753410965,
      "mom_6m": 0.10348892712988844,
      "name": "Rockwell Automation",
      "tags": [
        "physical_ai"
      ],
      "score": 33.0,
      "subscores": {
        "revenue_growth": 9.0,
        "earnings_growth": 36.0,
        "gross_margin": 24.0,
        "profit_margin": 37.0,
        "roe": 61.0,
        "mom_3m": 59.0,
        "mom_6m": 39.0,
        "upside": 11.0,
        "forward_pe": 43.0
      },
      "rank": 44
    },
    {
      "ticker": "ZBRA",
      "price": 254.89999389648438,
      "market_cap": 12141751296.0,
      "revenue_growth": 0.143,
      "earnings_growth": 0.038,
      "gross_margin": 0.48182,
      "profit_margin": 0.07487,
      "roe": 0.11781,
      "forward_pe": 12.303845,
      "trailing_pe": 30.822247,
      "target_mean": 333.17764,
      "upside": 0.3070915966177088,
      "recommendation": "buy",
      "num_analysts": 17.0,
      "mom_3m": 0.10999823451477764,
      "mom_6m": -0.015259849773585188,
      "name": "Zebra Technologies",
      "tags": [
        "physical_ai"
      ],
      "score": 32.6,
      "subscores": {
        "revenue_growth": 18.0,
        "earnings_growth": 6.0,
        "gross_margin": 22.0,
        "profit_margin": 30.0,
        "roe": 35.0,
        "mom_3m": 43.0,
        "mom_6m": 33.0,
        "upside": 61.0,
        "forward_pe": 85.0
      },
      "rank": 45
    },
    {
      "ticker": "SYM",
      "price": 42.939998626708984,
      "market_cap": 25920034816.0,
      "revenue_growth": 0.231,
      "earnings_growth": null,
      "gross_margin": 0.2041,
      "profit_margin": -0.0029300002,
      "roe": -0.05732,
      "forward_pe": 59.523144,
      "trailing_pe": null,
      "target_mean": 65.67375,
      "upside": 0.529430649752058,
      "recommendation": "buy",
      "num_analysts": 16.0,
      "mom_3m": -0.26898199864284067,
      "mom_6m": -0.35967789755449797,
      "name": "Symbotic",
      "tags": [
        "physical_ai"
      ],
      "score": 29.9,
      "subscores": {
        "revenue_growth": 47.0,
        "earnings_growth": 50.0,
        "gross_margin": 9.0,
        "profit_margin": 13.0,
        "roe": 15.0,
        "mom_3m": 4.0,
        "mom_6m": 4.0,
        "upside": 89.0,
        "forward_pe": 17.0
      },
      "rank": 46
    },
    {
      "ticker": "TSLA",
      "price": 398.2300109863281,
      "market_cap": 1495566778368.0,
      "revenue_growth": 0.158,
      "earnings_growth": 0.083,
      "gross_margin": 0.19065,
      "profit_margin": 0.03946,
      "roe": 0.04901,
      "forward_pe": 155.9101,
      "trailing_pe": 358.74774,
      "target_mean": 425.235,
      "upside": 0.06781254116631352,
      "recommendation": "buy",
      "num_analysts": 40.0,
      "mom_3m": 0.01602244822990273,
      "mom_6m": -0.09198074575142745,
      "name": "Tesla",
      "tags": [
        "physical_ai",
        "ai"
      ],
      "score": 19.7,
      "subscores": {
        "revenue_growth": 20.0,
        "earnings_growth": 9.0,
        "gross_margin": 7.0,
        "profit_margin": 24.0,
        "roe": 26.0,
        "mom_3m": 33.0,
        "mom_6m": 28.0,
        "upside": 20.0,
        "forward_pe": 4.0
      },
      "rank": 47
    }
  ]
}